README.md
setup.py
PaperScissorRock/Game.py
PaperScissorRock/__init__.py
PaperScissorsRock_Lib.egg-info/PKG-INFO
PaperScissorsRock_Lib.egg-info/SOURCES.txt
PaperScissorsRock_Lib.egg-info/dependency_links.txt
PaperScissorsRock_Lib.egg-info/top_level.txt