Metadata-Version: 2.1
Name: PaperScissorsRock-Lib
Version: 1.0.1
Summary: Normal Paper Scissors Rock In a Lib
Home-page: UNKNOWN
Author: JasonTheDev
License: UNKNOWN
Platform: UNKNOWN
Classifier: Programming Language :: Python :: 3
Requires-Python: >=3.6
